fmorg/__init__.py
fmorg/__main__.py
fmorg/analyzer.py
fmorg/analyzer_improved.py
fmorg/analyzer_original_backup.py
fmorg/cli.py
fmorg/display.py
fmorg/organizer.py
fmorg-1.0.0.dist-info/licenses/LICENSE
fmorg-1.0.0.dist-info/METADATA
fmorg-1.0.0.dist-info/WHEEL
fmorg-1.0.0.dist-info/entry_points.txt
fmorg-1.0.0.dist-info/top_level.txt
fmorg-1.0.0.dist-info/RECORD
