Metadata-Version: 2.4
Name: fmorg
Version: 1.0.0
Summary: A smart file organization tool that automatically sorts files into folders based on intelligent filename analysis
Author: FMORG Team
License: MIT
Project-URL: Homepage, https://github.com/yourusername/fmorg
Project-URL: Repository, https://github.com/yourusername/fmorg
Project-URL: Bug Reports, https://github.com/yourusername/fmorg/issues
Project-URL: Documentation, https://github.com/yourusername/fmorg/blob/main/README.md
Keywords: file organization,file manager,file sorting,automation,cli tool,filename analysis,media organization,batch file operations
Classifier: Development Status :: 5 - Production/Stable
Classifier: Intended Audience :: End Users/Desktop
Classifier: Topic :: System :: Filesystems
Classifier: Topic :: Utilities
Classifier: License :: OSI Approved :: MIT License
Classifier: Programming Language :: Python :: 3
Classifier: Programming Language :: Python :: 3.8
Classifier: Programming Language :: Python :: 3.9
Classifier: Programming Language :: Python :: 3.10
Classifier: Programming Language :: Python :: 3.11
Classifier: Programming Language :: Python :: 3.12
Classifier: Operating System :: OS Independent
Classifier: Environment :: Console
Requires-Python: >=3.8
License-File: LICENSE
Requires-Dist: click>=8.0.0
Requires-Dist: colorama>=0.4.4
Provides-Extra: dev
Requires-Dist: pytest>=7.0.0; extra == "dev"
Requires-Dist: pytest-cov>=4.0.0; extra == "dev"
Requires-Dist: black>=22.0.0; extra == "dev"
Requires-Dist: ruff>=0.1.0; extra == "dev"
Requires-Dist: mypy>=1.0.0; extra == "dev"
Dynamic: license-file
